LICENSE.rst
MANIFEST.in
README.rst
SCRATCH.rst
setup.py
aaargh/__init__.py
aaargh/app.py
aaargh.egg-info/PKG-INFO
aaargh.egg-info/SOURCES.txt
aaargh.egg-info/dependency_links.txt
aaargh.egg-info/top_level.txt