Metadata-Version: 1.1
Name: aaargh
Version: 0.7.1
Summary: An astonishingly awesome application argument helper
Home-page: https://github.com/wbolster/aaargh
Author: Wouter Bolsterlee
Author-email: uws@xs4all.nl
License: BSD
Platform: UNKNOWN
Classifier: Development Status :: 4 - Beta
Classifier: Environment :: Console
Classifier: Intended Audience :: Developers
Classifier: License :: OSI Approved :: BSD License
Classifier: Programming Language :: Python :: 2
Classifier: Programming Language :: Python :: 2.6
Classifier: Programming Language :: Python :: 2.7
Classifier: Programming Language :: Python :: 3
Classifier: Topic :: Software Development :: Libraries :: Python Modules
Classifier: Topic :: Software Development :: User Interfaces
